package_name/__init__.py
package_name/comparar_imagens.py
imagem_processing_frr-0.0.1.dist-info/METADATA
imagem_processing_frr-0.0.1.dist-info/WHEEL
imagem_processing_frr-0.0.1.dist-info/top_level.txt
imagem_processing_frr-0.0.1.dist-info/RECORD
