Metadata-Version: 2.4
Name: imagem_processing_frr
Version: 0.0.1
Summary: Permite comparar duas imagens e gerar uma terceira imagem que destaca as diferencas em preto e branco.
Home-page: https://github.com/faustorramos/image-processing-pypi/
Author: faustoramos
Author-email: faustorobert@hotmail.com
Requires-Python: >=3.7
Requires-Dist: Pillow>=11.1.0
Dynamic: author
Dynamic: author-email
Dynamic: description
Dynamic: description-content-type
Dynamic: home-page
Dynamic: requires-dist
Dynamic: requires-python
Dynamic: summary
